ccdexplorer_fundamentals/__init__.py
ccdexplorer_fundamentals/block.py
ccdexplorer_fundamentals/ccdscan.py
ccdexplorer_fundamentals/celery_app.py
ccdexplorer_fundamentals/cis.py
ccdexplorer_fundamentals/cns.py
ccdexplorer_fundamentals/credential.py
ccdexplorer_fundamentals/enums.py
ccdexplorer_fundamentals/env.py
ccdexplorer_fundamentals/grpc_test.py
ccdexplorer_fundamentals/mongodb.py
ccdexplorer_fundamentals/node.py
ccdexplorer_fundamentals/pool.py
ccdexplorer_fundamentals/redis_client.py
ccdexplorer_fundamentals/rewards.py
ccdexplorer_fundamentals/tooter.py
ccdexplorer_fundamentals/transaction.py
ccdexplorer_fundamentals/user_v2.py
ccdexplorer_fundamentals/GRPCClient/__init__.py
ccdexplorer_fundamentals/GRPCClient/health_pb2.py
ccdexplorer_fundamentals/GRPCClient/health_pb2.pyi
ccdexplorer_fundamentals/GRPCClient/health_pb2_grpc.py
ccdexplorer_fundamentals/GRPCClient/kernel_pb2.py
ccdexplorer_fundamentals/GRPCClient/kernel_pb2.pyi
ccdexplorer_fundamentals/GRPCClient/kernel_pb2_grpc.py
ccdexplorer_fundamentals/GRPCClient/protocol_level_tokens_pb2.py
ccdexplorer_fundamentals/GRPCClient/protocol_level_tokens_pb2.pyi
ccdexplorer_fundamentals/GRPCClient/protocol_level_tokens_pb2_grpc.py
ccdexplorer_fundamentals/GRPCClient/service_pb2.py
ccdexplorer_fundamentals/GRPCClient/service_pb2.pyi
ccdexplorer_fundamentals/GRPCClient/service_pb2_grpc.py
ccdexplorer_fundamentals/GRPCClient/types_pb2.py
ccdexplorer_fundamentals/GRPCClient/types_pb2.pyi
ccdexplorer_fundamentals/GRPCClient/types_pb2_grpc.py
ccdexplorer_fundamentals/GRPCClient/wadze.py
ccdexplorer_fundamentals/GRPCClient/CCD_Types/__init__.py
ccdexplorer_fundamentals/GRPCClient/concordium/__init__.py
ccdexplorer_fundamentals/GRPCClient/concordium/health/__init__.py
ccdexplorer_fundamentals/GRPCClient/concordium/v2/__init__.py
ccdexplorer_fundamentals/GRPCClient/concordium/v2/plt/__init__.py
ccdexplorer_fundamentals/GRPCClient/queries/_CheckHealth.py
ccdexplorer_fundamentals/GRPCClient/queries/_GetAccountInfo.py
ccdexplorer_fundamentals-0.3.20.dist-info/licenses/LICENSE.md
ccdexplorer_fundamentals-0.3.20.dist-info/METADATA
ccdexplorer_fundamentals-0.3.20.dist-info/WHEEL
ccdexplorer_fundamentals-0.3.20.dist-info/top_level.txt
ccdexplorer_fundamentals-0.3.20.dist-info/RECORD
