Metadata-Version: 2.4
Name: ccdexplorer-fundamentals
Version: 0.3.20
Summary: Shared code for CCDExplorer.io and its Notification Bot.
Home-page: https://github.com/ccdexplorer/ccdexplorer-fundamentals
Author: Sander de Ruiter
Author-email: sdr@ccdexplorer.io
License: Apache-2.0
License-File: LICENSE.md
Requires-Dist: rich
Requires-Dist: python-dateutil
Requires-Dist: base58
Requires-Dist: eth-hash
Requires-Dist: pycryptodome
Requires-Dist: pytest
Requires-Dist: leb128
Requires-Dist: pydantic
Requires-Dist: pymongo
Requires-Dist: motor
Requires-Dist: requests
Requires-Dist: apprise
Requires-Dist: py-graphql-client
Requires-Dist: chardet
Requires-Dist: pre-commit
Requires-Dist: cbor2
Dynamic: author
Dynamic: author-email
Dynamic: description
Dynamic: description-content-type
Dynamic: home-page
Dynamic: license
Dynamic: license-file
Dynamic: requires-dist
Dynamic: summary
